{
"vertices":[
{"id":"0","name":"wall","Leaves":[{"name":"wall","frequency":0.366667 }],"frequency":0.305556},
{"id":"1","name":"table","Leaves":[{"name":"table","frequency":0.76 }],"frequency":0.527778},
{"id":"2","name":"floor","Leaves":[],"frequency":0.694444},
{"id":"3","name":"bowl","Leaves":[],"frequency":0.416667},
{"id":"4","name":"clothing_rack","Leaves":[{"name":"clothing_rack","frequency":0.588235 }],"frequency":0.277778},
{"id":"5","name":"shelf","Leaves":[{"name":"shelf","frequency":0.652174 }],"frequency":0.416667},
{"id":"6","name":"bookshelf","Leaves":[{"name":"bookshelf","frequency":0.545454 }],"frequency":0.333333},
{"id":"7","name":"chair","Leaves":[{"name":"chair","frequency":0.375 }],"frequency":0.0833333},
{"id":"8","name":"ceiling","Leaves":[{"name":"ceiling","frequency":0.75 }],"frequency":0.25}
],
"rules":[
{"id":"0","source":"8","target":"0","factor":"proximity"},
{"id":"1","source":"5","target":"5","factor":"proximity"},
{"id":"2","source":"6","target":"6","factor":"proximity"},
{"id":"3","source":"4","target":"4","factor":"proximity"},
{"id":"4","source":"6","target":"5","factor":"proximity"},
{"id":"5","source":"4","target":"5","factor":"proximity"},
{"id":"6","source":"7","target":"1","factor":"proximity"},
{"id":"7","source":"7","target":"7","factor":"proximity"},
{"id":"8","source":"1","target":"1","factor":"proximity"},
{"id":"9","source":"0","target":"0","factor":"proximity"},
{"id":"10","source":"6","target":"4","factor":"proximity"},
{"id":"11","source":"5","target":"0","factor":"proximity"},
{"id":"12","source":"6","target":"7","factor":"proximity"},
{"id":"13","source":"6","target":"1","factor":"proximity"},
{"id":"14","source":"8","target":"4","factor":"proximity"},
{"id":"15","source":"5","target":"1","factor":"proximity"},
{"id":"16","source":"1","target":"1","factor":"orientation_parallel"},
{"id":"17","source":"6","target":"6","factor":"orientation_parallel"},
{"id":"18","source":"0","target":"0","factor":"orientation_parallel"},
{"id":"19","source":"0","target":"8","factor":"orientation_parallel"},
{"id":"20","source":"8","target":"0","factor":"orientation_parallel"},
{"id":"21","source":"8","target":"8","factor":"orientation_parallel"},
{"id":"22","source":"5","target":"4","factor":"orientation_parallel"},
{"id":"23","source":"4","target":"4","factor":"orientation_parallel"},
{"id":"24","source":"5","target":"5","factor":"orientation_parallel"},
{"id":"25","source":"1","target":"7","factor":"orientation_perpendicular"},
{"id":"26","source":"6","target":"1","factor":"orientation_perpendicular"},
{"id":"27","source":"6","target":"6","factor":"orientation_perpendicular"},
{"id":"28","source":"0","target":"5","factor":"orientation_perpendicular"},
{"id":"29","source":"5","target":"0","factor":"orientation_perpendicular"},
{"id":"30","source":"4","target":"4","factor":"symmetry"},
{"id":"31","source":"5","target":"5","factor":"symmetry"},
{"id":"32","source":"7","target":"7","factor":"symmetry"},
{"id":"33","source":"2","target":"0","factor":"vertical-support"},
{"id":"34","source":"2","target":"1","factor":"vertical-support"},
{"id":"35","source":"8","target":"6","factor":"horizontal-support"},
{"id":"36","source":"8","target":"2","factor":"horizontal-support"},
{"id":"37","source":"3","target":"2","factor":"horizontal-support"}
],
"probability":[
{"id":"0","value":0.166667},
{"id":"1","value":0.138889},
{"id":"2","value":0.111111},
{"id":"3","value":0.111111},
{"id":"4","value":0.0833333},
{"id":"5","value":0.0833333},
{"id":"6","value":0.0833333},
{"id":"7","value":0.0833333},
{"id":"8","value":0.0833333},
{"id":"9","value":0.0555556},
{"id":"10","value":0.0555556},
{"id":"11","value":0.0555556},
{"id":"12","value":0.0555556},
{"id":"13","value":0.0555556},
{"id":"14","value":0.0555556},
{"id":"15","value":0.0555556},
{"id":"16","value":0.111111},
{"id":"17","value":0.138889},
{"id":"18","value":0.166667},
{"id":"19","value":0.0833333},
{"id":"20","value":0.0833333},
{"id":"21","value":0.111111},
{"id":"22","value":0.111111},
{"id":"23","value":0.111111},
{"id":"24","value":0.0833333},
{"id":"25","value":0.0833333},
{"id":"26","value":0.0833333},
{"id":"27","value":0.0833333},
{"id":"28","value":0.0833333},
{"id":"29","value":0.0833333},
{"id":"30","value":0.0833333},
{"id":"31","value":0.0833333},
{"id":"32","value":0.0833333},
{"id":"33","value":0.111111},
{"id":"34","value":0.111111},
{"id":"35","value":0.0277778},
{"id":"36","value":0.0277778},
{"id":"37","value":0.0555556}
]}