{
"vertices":[
{"id":"0","name":"chair","Leaves":[{"name":"chair","frequency":0.321429 }],"frequency":0.692308},
{"id":"1","name":"table","Leaves":[{"name":"table","frequency":0.75 }],"frequency":0.692308},
{"id":"2","name":"chair","Leaves":[{"name":"chair","frequency":0.321429 }],"frequency":6.19374e-43}
],
"rules":[
{"id":"0","source":"0","target":"1","factor":"proximity"},
{"id":"1","source":"0","target":"1","factor":"orientation_parallel"},
{"id":"2","source":"1","target":"0","factor":"orientation_parallel"},
{"id":"3","source":"0","target":"1","factor":"orientation_perpendicular"},
{"id":"4","source":"0","target":"2","factor":"proximity"},
{"id":"5","source":"0","target":"2","factor":"orientation_parallel"},
{"id":"6","source":"2","target":"1","factor":"proximity"},
{"id":"7","source":"2","target":"1","factor":"orientation_parallel"},
{"id":"8","source":"1","target":"2","factor":"orientation_parallel"},
{"id":"9","source":"2","target":"1","factor":"orientation_perpendicular"},
{"id":"10","source":"1","target":"1","factor":"proximity"},
{"id":"11","source":"1","target":"1","factor":"orientation_parallel"}
],
"probability":[
{"id":"0","value":0.615385},
{"id":"1","value":0.692308},
{"id":"2","value":0.153846},
{"id":"3","value":0.307692},
{"id":"4","value":0.461538},
{"id":"5","value":0.307692},
{"id":"6","value":0.615385},
{"id":"7","value":0.692308},
{"id":"8","value":0.153846},
{"id":"9","value":0.307692},
{"id":"10","value":0.0769231},
{"id":"11","value":0.153846}
]}