{
"vertices":[
{"id":"0","name":"unknown","Leaves":[],"frequency":0.4},
{"id":"1","name":"paper","Leaves":[{"name":"money","frequency":1 },{"name":"motherlode","frequency":1 }],"frequency":0.7},
{"id":"2","name":"stove_burner","Leaves":[],"frequency":0.6},
{"id":"3","name":"bottle.n.01","Leaves":[{"name":"bottle","frequency":1 },{"name":"thermos","frequency":1 },{"name":"laundry_detergent_jug","frequency":1 },{"name":"poison","frequency":1 }],"frequency":0.4},
{"id":"4","name":"coffee_machine","Leaves":[],"frequency":0.2},
{"id":"5","name":"magnet","Leaves":[],"frequency":0.3},
{"id":"6","name":"wall","Leaves":[{"name":"wall","frequency":0.689655 }],"frequency":0.5},
{"id":"7","name":"box","Leaves":[],"frequency":0.4},
{"id":"8","name":"paper_towel","Leaves":[],"frequency":0.2},
{"id":"9","name":"sink","Leaves":[],"frequency":0.575},
{"id":"10","name":"floor","Leaves":[],"frequency":0.8},
{"id":"11","name":"paper_towel_dispenser","Leaves":[],"frequency":0.2},
{"id":"12","name":"kitchen_counter","Leaves":[],"frequency":0.575},
{"id":"13","name":"cabinet","Leaves":[],"frequency":0.4},
{"id":"14","name":"garbage_bin","Leaves":[{"name":"garbage_bin","frequency":0.848485 }],"frequency":0.7},
{"id":"15","name":"window","Leaves":[],"frequency":0.2},
{"id":"16","name":"door","Leaves":[],"frequency":0.5},
{"id":"17","name":"counter","Leaves":[],"frequency":0.4},
{"id":"18","name":"faucet","Leaves":[],"frequency":0.4},
{"id":"19","name":"microwave","Leaves":[],"frequency":0.325},
{"id":"20","name":"refridgerator","Leaves":[],"frequency":0.7},
{"id":"21","name":"pot","Leaves":[],"frequency":0.4}
],
"rules":[
{"id":"0","source":"12","target":"9","factor":"proximity"},
{"id":"1","source":"7","target":"9","factor":"proximity"},
{"id":"2","source":"7","target":"14","factor":"proximity"},
{"id":"3","source":"14","target":"12","factor":"proximity"},
{"id":"4","source":"14","target":"14","factor":"proximity"},
{"id":"5","source":"7","target":"6","factor":"proximity"},
{"id":"6","source":"12","target":"19","factor":"proximity"},
{"id":"7","source":"14","target":"9","factor":"proximity"},
{"id":"8","source":"9","target":"6","factor":"proximity"},
{"id":"9","source":"17","target":"19","factor":"proximity"},
{"id":"10","source":"7","target":"19","factor":"proximity"},
{"id":"11","source":"13","target":"11","factor":"proximity"},
{"id":"12","source":"7","target":"14","factor":"orientation_parallel"},
{"id":"13","source":"14","target":"14","factor":"orientation_parallel"},
{"id":"14","source":"14","target":"12","factor":"orientation_parallel"},
{"id":"15","source":"14","target":"9","factor":"orientation_parallel"},
{"id":"16","source":"12","target":"9","factor":"orientation_parallel"},
{"id":"17","source":"19","target":"12","factor":"orientation_parallel"},
{"id":"18","source":"6","target":"6","factor":"orientation_parallel"},
{"id":"19","source":"6","target":"7","factor":"orientation_parallel"},
{"id":"20","source":"6","target":"14","factor":"orientation_parallel"},
{"id":"21","source":"7","target":"6","factor":"orientation_parallel"},
{"id":"22","source":"9","target":"19","factor":"orientation_parallel"},
{"id":"23","source":"9","target":"7","factor":"orientation_parallel"},
{"id":"24","source":"6","target":"9","factor":"orientation_perpendicular"},
{"id":"25","source":"9","target":"6","factor":"orientation_perpendicular"},
{"id":"26","source":"7","target":"12","factor":"orientation_perpendicular"},
{"id":"27","source":"14","target":"12","factor":"orientation_perpendicular"},
{"id":"28","source":"18","target":"3","factor":"vertical-support"},
{"id":"29","source":"14","target":"17","factor":"vertical-support"},
{"id":"30","source":"17","target":"18","factor":"vertical-support"},
{"id":"31","source":"18","target":"10","factor":"vertical-support"},
{"id":"32","source":"14","target":"19","factor":"vertical-support"},
{"id":"33","source":"14","target":"7","factor":"vertical-support"},
{"id":"34","source":"14","target":"4","factor":"vertical-support"},
{"id":"35","source":"7","target":"0","factor":"vertical-support"},
{"id":"36","source":"9","target":"5","factor":"vertical-support"},
{"id":"37","source":"14","target":"9","factor":"vertical-support"},
{"id":"38","source":"14","target":"13","factor":"vertical-support"},
{"id":"39","source":"14","target":"1","factor":"vertical-support"},
{"id":"40","source":"19","target":"11","factor":"vertical-support"},
{"id":"41","source":"18","target":"13","factor":"vertical-support"},
{"id":"42","source":"18","target":"9","factor":"vertical-support"},
{"id":"43","source":"9","target":"7","factor":"vertical-support"},
{"id":"44","source":"14","target":"8","factor":"vertical-support"},
{"id":"45","source":"17","target":"4","factor":"vertical-support"},
{"id":"46","source":"18","target":"1","factor":"vertical-support"},
{"id":"47","source":"18","target":"21","factor":"vertical-support"},
{"id":"48","source":"18","target":"20","factor":"vertical-support"},
{"id":"49","source":"18","target":"2","factor":"vertical-support"},
{"id":"50","source":"6","target":"10","factor":"vertical-support"},
{"id":"51","source":"13","target":"20","factor":"vertical-support"},
{"id":"52","source":"20","target":"2","factor":"vertical-support"},
{"id":"53","source":"21","target":"3","factor":"vertical-support"},
{"id":"54","source":"2","target":"9","factor":"vertical-support"},
{"id":"55","source":"9","target":"21","factor":"vertical-support"},
{"id":"56","source":"21","target":"20","factor":"vertical-support"},
{"id":"57","source":"21","target":"0","factor":"vertical-support"},
{"id":"58","source":"21","target":"5","factor":"vertical-support"},
{"id":"59","source":"21","target":"7","factor":"vertical-support"},
{"id":"60","source":"21","target":"16","factor":"vertical-support"},
{"id":"61","source":"16","target":"10","factor":"vertical-support"},
{"id":"62","source":"16","target":"14","factor":"vertical-support"},
{"id":"63","source":"16","target":"20","factor":"vertical-support"},
{"id":"64","source":"16","target":"15","factor":"vertical-support"},
{"id":"65","source":"16","target":"2","factor":"vertical-support"},
{"id":"66","source":"16","target":"1","factor":"vertical-support"},
{"id":"67","source":"16","target":"8","factor":"vertical-support"},
{"id":"68","source":"3","target":"17","factor":"vertical-support"},
{"id":"69","source":"18","target":"14","factor":"support"},
{"id":"70","source":"9","target":"11","factor":"horizontal-support"},
{"id":"71","source":"9","target":"1","factor":"horizontal-support"}
],
"probability":[
{"id":"0","value":0.225},
{"id":"1","value":0.125},
{"id":"2","value":0.125},
{"id":"3","value":0.1},
{"id":"4","value":0.1},
{"id":"5","value":0.075},
{"id":"6","value":0.05},
{"id":"7","value":0.05},
{"id":"8","value":0.05},
{"id":"9","value":0.05},
{"id":"10","value":0.05},
{"id":"11","value":0.05},
{"id":"12","value":0.125},
{"id":"13","value":0.075},
{"id":"14","value":0.1},
{"id":"15","value":0.075},
{"id":"16","value":0.375},
{"id":"17","value":0.175},
{"id":"18","value":0.15},
{"id":"19","value":0.075},
{"id":"20","value":0.075},
{"id":"21","value":0.075},
{"id":"22","value":0.075},
{"id":"23","value":0.075},
{"id":"24","value":0.075},
{"id":"25","value":0.075},
{"id":"26","value":0.075},
{"id":"27","value":0.1},
{"id":"28","value":0.3},
{"id":"29","value":0.2},
{"id":"30","value":0.2},
{"id":"31","value":0.3},
{"id":"32","value":0.3},
{"id":"33","value":0.1},
{"id":"34","value":0.1},
{"id":"35","value":0.1},
{"id":"36","value":0.1},
{"id":"37","value":0.1},
{"id":"38","value":0.1},
{"id":"39","value":0.1},
{"id":"40","value":0.1},
{"id":"41","value":0.1},
{"id":"42","value":0.2},
{"id":"43","value":0.1},
{"id":"44","value":0.1},
{"id":"45","value":0.1},
{"id":"46","value":0.2},
{"id":"47","value":0.1},
{"id":"48","value":0.3},
{"id":"49","value":0.1},
{"id":"50","value":0.3},
{"id":"51","value":0.1},
{"id":"52","value":0.1},
{"id":"53","value":0.1},
{"id":"54","value":0.1},
{"id":"55","value":0.2},
{"id":"56","value":0.1},
{"id":"57","value":0.1},
{"id":"58","value":0.1},
{"id":"59","value":0.1},
{"id":"60","value":0.1},
{"id":"61","value":0.1},
{"id":"62","value":0.1},
{"id":"63","value":0.1},
{"id":"64","value":0.1},
{"id":"65","value":0.1},
{"id":"66","value":0.1},
{"id":"67","value":0.1},
{"id":"68","value":0.1},
{"id":"69","value":0.3},
{"id":"70","value":0.1},
{"id":"71","value":0.1}
]}