{
"vertices":[
{"id":"0","name":"coffee_packet","Leaves":[],"frequency":0.2},
{"id":"1","name":"hot_water_heater","Leaves":[],"frequency":0.4},
{"id":"2","name":"plant","Leaves":[],"frequency":0.4},
{"id":"3","name":"room","Leaves":[],"frequency":0.9995},
{"id":"4","name":"manilla_envelope","Leaves":[],"frequency":0.2},
{"id":"5","name":"table","Leaves":[],"frequency":0.8},
{"id":"6","name":"picture","Leaves":[],"frequency":0.4},
{"id":"7","name":"bowl","Leaves":[],"frequency":0.4},
{"id":"8","name":"counter","Leaves":[],"frequency":0.6},
{"id":"9","name":"desk","Leaves":[],"frequency":0.6}
],
"rules":[
{"id":"0","source":"3","target":"5","factor":"vertical-support"},
{"id":"1","source":"3","target":"9","factor":"vertical-support"},
{"id":"2","source":"0","target":"8","factor":"vertical-support"},
{"id":"3","source":"3","target":"0","factor":"vertical-support"},
{"id":"4","source":"0","target":"4","factor":"vertical-support"},
{"id":"5","source":"0","target":"6","factor":"vertical-support"},
{"id":"6","source":"2","target":"7","factor":"vertical-support"},
{"id":"7","source":"9","target":"1","factor":"vertical-support"}
],
"probability":[
{"id":"0","value":0.2},
{"id":"1","value":0.4},
{"id":"2","value":0.2},
{"id":"3","value":0.2},
{"id":"4","value":0.2},
{"id":"5","value":0.2},
{"id":"6","value":0.2},
{"id":"7","value":0.2}
]}